proprogram/__init__.py
proprogram/program1.py
proprogram/program2.py
proprogram/program3.py
proprogram/program3.py.py
proprogram/program4.py
proprogram/program5a.py
proprogram/program5b.py
proprogram-1.0.0.dist-info/METADATA
proprogram-1.0.0.dist-info/WHEEL
proprogram-1.0.0.dist-info/top_level.txt
proprogram-1.0.0.dist-info/RECORD
