Metadata-Version: 2.4
Name: proprogram
Version: 1.0.0
Summary: Collection of AI/ML programs in Python
Author: Divyan S
Requires-Python: >=3.8
Requires-Dist: numpy
Requires-Dist: tensorflow
Requires-Dist: matplotlib
Requires-Dist: scikit-learn
Requires-Dist: pandas
Requires-Dist: speechrecognition
Requires-Dist: pyttsx3
Dynamic: author
Dynamic: requires-dist
Dynamic: requires-python
Dynamic: summary
